balekit/__init__.py
balekit/client/client.py
balekit/client/methods/__init__.py
balekit/client/methods/ban_chat_member.py
balekit/client/methods/copy_message.py
balekit/client/methods/create_chat_invite_link.py
balekit/client/methods/delete_chat_photo.py
balekit/client/methods/delete_message.py
balekit/client/methods/edit_message_text.py
balekit/client/methods/export_chat_invite_link.py
balekit/client/methods/forward_message.py
balekit/client/methods/get_chat.py
balekit/client/methods/get_chat_members_count.py
balekit/client/methods/get_me.py
balekit/client/methods/leave_chat.py
balekit/client/methods/pin_chat_message.py
balekit/client/methods/promote_chat_member.py
balekit/client/methods/revoke_chat_invite_link.py
balekit/client/methods/send_animation.py
balekit/client/methods/send_audio.py
balekit/client/methods/send_contact.py
balekit/client/methods/send_document.py
balekit/client/methods/send_location.py
balekit/client/methods/send_message.py
balekit/client/methods/send_photo.py
balekit/client/methods/send_video.py
balekit/client/methods/send_voice.py
balekit/client/methods/set_chat_description.py
balekit/client/methods/set_chat_photo.py
balekit/client/methods/set_chat_title.py
balekit/client/methods/unban_chat_member.py
balekit/client/methods/unpin_all_chat_messages.py
balekit/client/methods/unpin_chat_message.py
balekit/client/methods/upload_sticker_file.py
balekit-0.0.3.dist-info/LICENSE
balekit-0.0.3.dist-info/METADATA
balekit-0.0.3.dist-info/WHEEL
balekit-0.0.3.dist-info/top_level.txt
balekit-0.0.3.dist-info/RECORD
