Metadata-Version: 2.2
Name: balekit
Version: 0.0.3
Summary: A tool for developing bots in Bale messenger!
Author-email: Mohammad Parsa Mortazavi <mohammadparsa9053@gmail.com>
Project-URL: Homepage, https://github.com/mpmms/balekit
Project-URL: Issues, https://github.com/mpmms/balekit/issues
Classifier: Programming Language :: Python :: 3
Classifier: License :: OSI Approved :: MIT License
Classifier: Operating System :: OS Independent
Requires-Python: >=3.8
License-File: LICENSE
